AWRS.py
README.md
setup.py
AWRS.egg-info/PKG-INFO
AWRS.egg-info/SOURCES.txt
AWRS.egg-info/dependency_links.txt
AWRS.egg-info/entry_points.txt
AWRS.egg-info/requires.txt
AWRS.egg-info/top_level.txt