Metadata-Version: 1.0
Name: AWRS
Version: 2019.8.9.1757
Summary: weather utilities
Home-page: https://github.com/wdbm/AWRS
Author: Will Breaden Madden
Author-email: wbm@protonmail.ch
License: GPLv3
Platform: UNKNOWN
